thousandeyes_sdk/endpoint_labels/__init__.py
thousandeyes_sdk/endpoint_labels/py.typed
thousandeyes_sdk/endpoint_labels/api/__init__.py
thousandeyes_sdk/endpoint_labels/api/endpoint_agent_labels_api.py
thousandeyes_sdk/endpoint_labels/models/__init__.py
thousandeyes_sdk/endpoint_labels/models/error.py
thousandeyes_sdk/endpoint_labels/models/expand_label_options.py
thousandeyes_sdk/endpoint_labels/models/filter.py
thousandeyes_sdk/endpoint_labels/models/filter_type.py
thousandeyes_sdk/endpoint_labels/models/label.py
thousandeyes_sdk/endpoint_labels/models/label_filter_mode.py
thousandeyes_sdk/endpoint_labels/models/label_request.py
thousandeyes_sdk/endpoint_labels/models/label_response.py
thousandeyes_sdk/endpoint_labels/models/labels.py
thousandeyes_sdk/endpoint_labels/models/link.py
thousandeyes_sdk/endpoint_labels/models/match_type.py
thousandeyes_sdk/endpoint_labels/models/pagination_next_and_self_link.py
thousandeyes_sdk/endpoint_labels/models/self_links.py
thousandeyes_sdk/endpoint_labels/models/unauthorized_error.py
thousandeyes_sdk/endpoint_labels/models/validation_error.py
thousandeyes_sdk/endpoint_labels/models/validation_error_item.py
thousandeyes_sdk_endpoint_labels-2.23.0.dist-info/licenses/LICENSE
thousandeyes_sdk_endpoint_labels-2.23.0.dist-info/licenses/NOTICE
thousandeyes_sdk_endpoint_labels-2.23.0.dist-info/METADATA
thousandeyes_sdk_endpoint_labels-2.23.0.dist-info/WHEEL
thousandeyes_sdk_endpoint_labels-2.23.0.dist-info/top_level.txt
thousandeyes_sdk_endpoint_labels-2.23.0.dist-info/RECORD
